promptflow_python/__init__.py
promptflow_python/_version.py
promptflow_python/start_server.py
promptflow_python/package_data/runit/promptflow-python/finish
promptflow_python/package_data/runit/promptflow-python/run
promptflow_python/package_data/runit/token-provider/run
promptflow_python/package_data/runit/token-provider/token_provider.py
promptflow_python/package_data/scripts/auto_detect_env.sh
promptflow_python/package_data/scripts/start.sh
promptflow_python/package_data/scripts/warmpool.sh
promptflow_python_bundle-0.3.0.dist-info/METADATA
promptflow_python_bundle-0.3.0.dist-info/WHEEL
promptflow_python_bundle-0.3.0.dist-info/entry_points.txt
promptflow_python_bundle-0.3.0.dist-info/top_level.txt
promptflow_python_bundle-0.3.0.dist-info/RECORD
