Metadata-Version: 2.1
Name: promptflow-python-bundle
Version: 0.3.0
Summary: Allow you to create your own promptflow python base images
Author: Microsoft Corporation
Classifier: Programming Language :: Python :: 3
Classifier: License :: Other/Proprietary License
Classifier: Operating System :: OS Independent
Requires-Python: <4.0,>=3.8
Requires-Dist: gunicorn <23.0.0,>=22.0.0
Requires-Dist: uvicorn <1.0.0,>=0.27.0
Requires-Dist: promptflow-tools >=1.4.0
Requires-Dist: promptflow-core[azureml-serving] >=1.12.0
